amzconfig/__init__.py
amzconfig/config.py
amzconfig-0.1.0.dist-info/METADATA
amzconfig-0.1.0.dist-info/WHEEL
amzconfig-0.1.0.dist-info/top_level.txt
amzconfig-0.1.0.dist-info/RECORD
