Metadata-Version: 2.4
Name: amzconfig
Version: 0.1.0
Summary: An amazing config loader tool.
Requires-Python: >=3.10
Requires-Dist: pyyaml>=6.0.2
